{
  "project_info": {
    "project_number": "844671784046",
    "project_id": "taskignite",
    "storage_bucket": "taskignite.appspot.com"
  },
  "client": [
    {
      "client_info": {
        "mobilesdk_app_id": "1:844671784046:android:6a398be7fcbee9b8c2c27f",
        "android_client_info": {
          "package_name": "com.example.ignite_crud_firebase"
        }
      },
      "oauth_client": [],
      "api_key": [
        {
          "current_key": "AIzaSyB_h28Ef02rVtKy5arAom0eDeMtdPzv4tU"
        }
      ],
      "services": {
        "appinvite_service": {
          "other_platform_oauth_client": []
        }
      }
    }
  ],
  "configuration_version": "1"
}